pycrackwatch/__init__.py
pycrackwatch/api.py
pycrackwatch/crackwatch.py
pycrackwatch/models.py
pycrackwatch-1.0.0.dist-info/METADATA
pycrackwatch-1.0.0.dist-info/RECORD
pycrackwatch-1.0.0.dist-info/WHEEL
pycrackwatch-1.0.0.dist-info/top_level.txt
