Metadata-Version: 2.1
Name: pycrackwatch
Version: 1.0.0
Summary: A Python wrapper for the CrackWatch API
Home-page: UNKNOWN
Author: cominixo
Author-email: lucasdutraluza@gmail.com
License: UNKNOWN
Platform: UNKNOWN
